{"data":{"identifier":"article-code","script":"<script>\n    import {Article} from \"@kahi-ui/framework\";\n</script>\n\n\n<Article>\n    <code>import * as Kahi from \"@kahi-ui/framework\";</code>\n\n    <br />\n    <br />\n\n    <pre>import math from \"a-math-library\";\n\nconst result = math.add(1, 1);\nconsole.log(\"Our value is:\", result);</pre>\n\n    <code>import * as Kahi from \"@kahi-ui/framework\";</code>\n\n            <p>\n            This has nested <code>code tags</code>!\n        </p>\n\n        <blockquote>\n            <p>\n                This has nested <code>code tags</code>!\n            </p>\n        </blockquote>\n\n        <ul>\n            <li>\n                This has nested <code>code tags</code>!\n            </li>\n        </ul>\n</Article>","syntax":"svelte","title":"Article Code"}}