{"data":{"properties":{"created_at":0,"events":{},"identifier":"surfaces/hero","modified_at":1628541635548.9802,"properties":{"Hero.Container":[{"name":"palette","description":"<p>Alters the displayed color scheme.</p>\n","types":["accent","dark","light","alert","affirmative","negative"]}]},"sections":[{"identifier":"hero","level":1,"text":"Hero"},{"identifier":"imports","level":2,"text":"Imports"},{"identifier":"palette","level":2,"text":"Palette"}],"snippets":[{"identifier":"hero-preview","script":"<script>\n    import {Button, Hero} from \"@kahi-ui/framework\";\n</script>\n\n<Hero.Container\n    palette=\"negative\"\n    height=\"viewport-100\"\n>\n    <Hero.Header>404</Hero.Header>\n    <Hero.Section>\n        The page you tried to access is missing or no\n        longer available.\n    </Hero.Section>\n\n    <Hero.Footer>\n        <Button palette=\"light\" variation=\"clear\">\n            Go Back\n        </Button>\n        <Button palette=\"accent\">Submit Ticket</Button>\n    </Hero.Footer>\n</Hero.Container>","syntax":"svelte","title":"Hero Preview"},{"identifier":"hero-imports","script":"<script>\n    import {Hero} from \"@kahi-ui/framework\";\n\n    const {Container, Footer, Header, Section} = Hero;\n</script>","syntax":"html","title":"Hero Imports"},{"identifier":"hero-palette","script":"<script>\n    import {\n        Button,\n        Hero,\n        Stack,\n    } from \"@kahi-ui/framework\";\n</script>\n\n<Stack spacing=\"medium\">\n    <Hero.Container>\n        <Hero.Header>404 (DEFAULT)</Hero.Header>\n        <Hero.Section>\n            The page you tried to access is missing or\n            no longer available.\n        </Hero.Section>\n\n        <Hero.Footer>\n            <Button palette=\"accent\" variation=\"clear\">\n                Go Back\n            </Button>\n            <Button palette=\"negative\"\n                >Submit Ticket\n            </Button>\n        </Hero.Footer>\n    </Hero.Container>\n\n    <Hero.Container palette=\"accent\">\n        <Hero.Header>404 (ACCENT)</Hero.Header>\n        <Hero.Section>\n            The page you tried to access is missing or\n            no longer available.\n        </Hero.Section>\n\n        <Hero.Footer>\n            <Button palette=\"light\" variation=\"clear\">\n                Go Back\n            </Button>\n            <Button palette=\"negative\"\n                >Submit Ticket\n            </Button>\n        </Hero.Footer>\n    </Hero.Container>\n\n    <Hero.Container palette=\"dark\">\n        <Hero.Header>404 (DARK)</Hero.Header>\n        <Hero.Section>\n            The page you tried to access is missing or\n            no longer available.\n        </Hero.Section>\n\n        <Hero.Footer>\n            <Button palette=\"light\" variation=\"clear\">\n                Go Back\n            </Button>\n            <Button palette=\"negative\"\n                >Submit Ticket\n            </Button>\n        </Hero.Footer>\n    </Hero.Container>\n\n    <Hero.Container palette=\"light\">\n        <Hero.Header>404 (LIGHT)</Hero.Header>\n        <Hero.Section>\n            The page you tried to access is missing or\n            no longer available.\n        </Hero.Section>\n\n        <Hero.Footer>\n            <Button palette=\"dark\" variation=\"clear\">\n                Go Back\n            </Button>\n            <Button palette=\"negative\"\n                >Submit Ticket\n            </Button>\n        </Hero.Footer>\n    </Hero.Container>\n\n    <Hero.Container palette=\"alert\">\n        <Hero.Header>404 (ALERT)</Hero.Header>\n        <Hero.Section>\n            The page you tried to access is missing or\n            no longer available.\n        </Hero.Section>\n\n        <Hero.Footer>\n            <Button palette=\"light\" variation=\"clear\">\n                Go Back\n            </Button>\n            <Button palette=\"negative\"\n                >Submit Ticket\n            </Button>\n        </Hero.Footer>\n    </Hero.Container>\n\n    <Hero.Container palette=\"affirmative\">\n        <Hero.Header>404 (AFFIRMATIVE)</Hero.Header>\n        <Hero.Section>\n            The page you tried to access is missing or\n            no longer available.\n        </Hero.Section>\n\n        <Hero.Footer>\n            <Button palette=\"light\" variation=\"clear\">\n                Go Back\n            </Button>\n            <Button palette=\"negative\"\n                >Submit Ticket\n            </Button>\n        </Hero.Footer>\n    </Hero.Container>\n\n    <Hero.Container palette=\"negative\">\n        <Hero.Header>404 (NEGATIVE)</Hero.Header>\n        <Hero.Section>\n            The page you tried to access is missing or\n            no longer available.\n        </Hero.Section>\n\n        <Hero.Footer>\n            <Button palette=\"light\" variation=\"clear\">\n                Go Back\n            </Button>\n            <Button palette=\"accent\"\n                >Submit Ticket\n            </Button>\n        </Hero.Footer>\n    </Hero.Container>\n</Stack>","syntax":"svelte","title":"Hero Palette"}],"title":"Hero"},"render":"<h1 id=\"hero\">Hero</h1>\n<p><code>Hero</code> is a multi-part surface pattern for displaying banner text with subtitling and actions, typically used for landing pages, error messages, and loading placeholders.</p>\n<iframe\n    class=\"snippet-repl\"\n    src=\"/repl/docs/surfaces/hero/hero-preview?rotation=horizontal\"\n    sandbox=\"allow-popups-to-escape-sandbox allow-scripts allow-popups allow-forms allow-pointer-lock allow-top-navigation allow-modals allow-same-origin\" loading=\"lazy\"\n></iframe>\n<a href=\"/repl/docs/surfaces/hero/hero-preview?rotation=horizontal\" hidden sveltekit:prefetch></a><h2 id=\"imports\">Imports</h2>\n<pre class=\"language-html snippet-highlight\"><code class=\"language-html\"><span class=\"token tag\"><span class=\"token tag\"><span class=\"token punctuation\">&lt;</span>script</span><span class=\"token punctuation\">></span></span><span class=\"token script\"><span class=\"token language-javascript\">\n    <span class=\"token keyword\">import</span> <span class=\"token punctuation\">{</span>Hero<span class=\"token punctuation\">}</span> <span class=\"token keyword\">from</span> <span class=\"token string\">\"@kahi-ui/framework\"</span><span class=\"token punctuation\">;</span>\n\n    <span class=\"token keyword\">const</span> <span class=\"token punctuation\">{</span>Container<span class=\"token punctuation\">,</span> Footer<span class=\"token punctuation\">,</span> Header<span class=\"token punctuation\">,</span> Section<span class=\"token punctuation\">}</span> <span class=\"token operator\">=</span> Hero<span class=\"token punctuation\">;</span>\n</span></span><span class=\"token tag\"><span class=\"token tag\"><span class=\"token punctuation\">&lt;/</span>script</span><span class=\"token punctuation\">></span></span></code></pre><h2 id=\"palette\">Palette</h2>\n<p>You can change the color palette of the <code>Hero</code> via the <code>palette</code> property.</p>\n<iframe\n    class=\"snippet-repl\"\n    src=\"/repl/docs/surfaces/hero/hero-palette?rotation=horizontal\"\n    sandbox=\"allow-popups-to-escape-sandbox allow-scripts allow-popups allow-forms allow-pointer-lock allow-top-navigation allow-modals allow-same-origin\" loading=\"lazy\"\n></iframe>\n<a href=\"/repl/docs/surfaces/hero/hero-palette?rotation=horizontal\" hidden sveltekit:prefetch></a>"}}