{"data":{"metadata":{"authors":{},"created_at":1645838554000,"identifier":"/docs/themeing/palettes","modified_at":1645838554000,"sections":[{"identifier":"palettes","level":1,"text":"Palettes"}],"snippets":[{"identifier":"palettes-preview","script":"<script>\n    import {Stack, Text} from \"@kahi-ui/framework\";\n</script>\n\n<Stack.Container spacing=\"medium\">\n    <div>\n        <Text is=\"strong\">ACCENT</Text>\n\n        <Stack.Container\n            orientation=\"horizontal\"\n            alignment_x=\"stretch\"\n        >\n            <div\n                data-height=\"icon-massive\"\n                style=\"background: hsl(var(--palettes-accent-background-lightest));\"\n            />\n\n            <div\n                data-height=\"icon-massive\"\n                style=\"background: hsl(var(--palettes-accent-background-lighter));\"\n            />\n\n            <div\n                data-height=\"icon-massive\"\n                style=\"background: hsl(var(--palettes-accent-background-light));\"\n            />\n\n            <div\n                data-height=\"icon-massive\"\n                style=\"background: hsl(var(--palettes-accent-background-normal));\"\n            />\n\n            <div\n                data-height=\"icon-massive\"\n                style=\"background: hsl(var(--palettes-accent-background-bold));\"\n            />\n\n            <div\n                data-height=\"icon-massive\"\n                style=\"background: hsl(var(--palettes-accent-background-bolder));\"\n            />\n\n            <div\n                data-height=\"icon-massive\"\n                style=\"background: hsl(var(--palettes-accent-background-boldest));\"\n            />\n        </Stack.Container>\n    </div>\n\n    <div>\n        <Text is=\"strong\">NEUTRAL</Text>\n\n        <Stack.Container\n            orientation=\"horizontal\"\n            alignment_x=\"stretch\"\n        >\n            <div\n                data-height=\"icon-massive\"\n                style=\"background: hsl(var(--palettes-neutral-background-lightest));\"\n            />\n\n            <div\n                data-height=\"icon-massive\"\n                style=\"background: hsl(var(--palettes-neutral-background-lighter));\"\n            />\n\n            <div\n                data-height=\"icon-massive\"\n                style=\"background: hsl(var(--palettes-neutral-background-light));\"\n            />\n\n            <div\n                data-height=\"icon-massive\"\n                style=\"background: hsl(var(--palettes-neutral-background-normal));\"\n            />\n\n            <div\n                data-height=\"icon-massive\"\n                style=\"background: hsl(var(--palettes-neutral-background-bold));\"\n            />\n\n            <div\n                data-height=\"icon-massive\"\n                style=\"background: hsl(var(--palettes-neutral-background-bolder));\"\n            />\n\n            <div\n                data-height=\"icon-massive\"\n                style=\"background: hsl(var(--palettes-neutral-background-boldest));\"\n            />\n        </Stack.Container>\n    </div>\n\n    <div>\n        <Text is=\"strong\">OFF</Text>\n\n        <Stack.Container\n            orientation=\"horizontal\"\n            alignment_x=\"stretch\"\n        >\n            <div\n                data-height=\"icon-massive\"\n                style=\"background: hsl(var(--palettes-off-background-lightest));\"\n            />\n\n            <div\n                data-height=\"icon-massive\"\n                style=\"background: hsl(var(--palettes-off-background-lighter));\"\n            />\n\n            <div\n                data-height=\"icon-massive\"\n                style=\"background: hsl(var(--palettes-off-background-light));\"\n            />\n\n            <div\n                data-height=\"icon-massive\"\n                style=\"background: hsl(var(--palettes-off-background-normal));\"\n            />\n\n            <div\n                data-height=\"icon-massive\"\n                style=\"background: hsl(var(--palettes-off-background-bold));\"\n            />\n\n            <div\n                data-height=\"icon-massive\"\n                style=\"background: hsl(var(--palettes-off-background-bolder));\"\n            />\n\n            <div\n                data-height=\"icon-massive\"\n                style=\"background: hsl(var(--palettes-off-background-boldest));\"\n            />\n        </Stack.Container>\n    </div>\n\n    <div>\n        <Text is=\"strong\">DARK</Text>\n\n        <Stack.Container\n            orientation=\"horizontal\"\n            alignment_x=\"stretch\"\n        >\n            <div\n                data-height=\"icon-massive\"\n                style=\"background: hsl(var(--palettes-dark-background-lightest));\"\n            />\n\n            <div\n                data-height=\"icon-massive\"\n                style=\"background: hsl(var(--palettes-dark-background-lighter));\"\n            />\n\n            <div\n                data-height=\"icon-massive\"\n                style=\"background: hsl(var(--palettes-dark-background-light));\"\n            />\n\n            <div\n                data-height=\"icon-massive\"\n                style=\"background: hsl(var(--palettes-dark-background-normal));\"\n            />\n\n            <div\n                data-height=\"icon-massive\"\n                style=\"background: hsl(var(--palettes-dark-background-bold));\"\n            />\n\n            <div\n                data-height=\"icon-massive\"\n                style=\"background: hsl(var(--palettes-dark-background-bolder));\"\n            />\n\n            <div\n                data-height=\"icon-massive\"\n                style=\"background: hsl(var(--palettes-dark-background-boldest));\"\n            />\n        </Stack.Container>\n    </div>\n\n    <div>\n        <Text is=\"strong\">LIGHT</Text>\n\n        <Stack.Container\n            orientation=\"horizontal\"\n            alignment_x=\"stretch\"\n        >\n            <div\n                data-height=\"icon-massive\"\n                style=\"background: hsl(var(--palettes-light-background-lightest));\"\n            />\n\n            <div\n                data-height=\"icon-massive\"\n                style=\"background: hsl(var(--palettes-light-background-lighter));\"\n            />\n\n            <div\n                data-height=\"icon-massive\"\n                style=\"background: hsl(var(--palettes-light-background-light));\"\n            />\n\n            <div\n                data-height=\"icon-massive\"\n                style=\"background: hsl(var(--palettes-light-background-normal));\"\n            />\n\n            <div\n                data-height=\"icon-massive\"\n                style=\"background: hsl(var(--palettes-light-background-bold));\"\n            />\n\n            <div\n                data-height=\"icon-massive\"\n                style=\"background: hsl(var(--palettes-light-background-bolder));\"\n            />\n\n            <div\n                data-height=\"icon-massive\"\n                style=\"background: hsl(var(--palettes-light-background-boldest));\"\n            />\n        </Stack.Container>\n    </div>\n\n    <div>\n        <Text is=\"strong\">ALERT</Text>\n\n        <Stack.Container\n            orientation=\"horizontal\"\n            alignment_x=\"stretch\"\n        >\n            <div\n                data-height=\"icon-massive\"\n                style=\"background: hsl(var(--palettes-alert-background-lightest));\"\n            />\n\n            <div\n                data-height=\"icon-massive\"\n                style=\"background: hsl(var(--palettes-alert-background-lighter));\"\n            />\n\n            <div\n                data-height=\"icon-massive\"\n                style=\"background: hsl(var(--palettes-alert-background-light));\"\n            />\n\n            <div\n                data-height=\"icon-massive\"\n                style=\"background: hsl(var(--palettes-alert-background-normal));\"\n            />\n\n            <div\n                data-height=\"icon-massive\"\n                style=\"background: hsl(var(--palettes-alert-background-bold));\"\n            />\n\n            <div\n                data-height=\"icon-massive\"\n                style=\"background: hsl(var(--palettes-alert-background-bolder));\"\n            />\n\n            <div\n                data-height=\"icon-massive\"\n                style=\"background: hsl(var(--palettes-alert-background-boldest));\"\n            />\n        </Stack.Container>\n    </div>\n\n    <div>\n        <Text is=\"strong\">AFFIRMATIVE</Text>\n\n        <Stack.Container\n            orientation=\"horizontal\"\n            alignment_x=\"stretch\"\n        >\n            <div\n                data-height=\"icon-massive\"\n                style=\"background: hsl(var(--palettes-affirmative-background-lightest));\"\n            />\n\n            <div\n                data-height=\"icon-massive\"\n                style=\"background: hsl(var(--palettes-affirmative-background-lighter));\"\n            />\n\n            <div\n                data-height=\"icon-massive\"\n                style=\"background: hsl(var(--palettes-affirmative-background-light));\"\n            />\n\n            <div\n                data-height=\"icon-massive\"\n                style=\"background: hsl(var(--palettes-affirmative-background-normal));\"\n            />\n\n            <div\n                data-height=\"icon-massive\"\n                style=\"background: hsl(var(--palettes-affirmative-background-bold));\"\n            />\n\n            <div\n                data-height=\"icon-massive\"\n                style=\"background: hsl(var(--palettes-affirmative-background-bolder));\"\n            />\n\n            <div\n                data-height=\"icon-massive\"\n                style=\"background: hsl(var(--palettes-affirmative-background-boldest));\"\n            />\n        </Stack.Container>\n    </div>\n\n    <div>\n        <Text is=\"strong\">INFORMATIVE</Text>\n\n        <Stack.Container\n            orientation=\"horizontal\"\n            alignment_x=\"stretch\"\n        >\n            <div\n                data-height=\"icon-massive\"\n                style=\"background: hsl(var(--palettes-informative-background-lightest));\"\n            />\n\n            <div\n                data-height=\"icon-massive\"\n                style=\"background: hsl(var(--palettes-informative-background-lighter));\"\n            />\n\n            <div\n                data-height=\"icon-massive\"\n                style=\"background: hsl(var(--palettes-informative-background-light));\"\n            />\n\n            <div\n                data-height=\"icon-massive\"\n                style=\"background: hsl(var(--palettes-informative-background-normal));\"\n            />\n\n            <div\n                data-height=\"icon-massive\"\n                style=\"background: hsl(var(--palettes-informative-background-bold));\"\n            />\n\n            <div\n                data-height=\"icon-massive\"\n                style=\"background: hsl(var(--palettes-informative-background-bolder));\"\n            />\n\n            <div\n                data-height=\"icon-massive\"\n                style=\"background: hsl(var(--palettes-informative-background-boldest));\"\n            />\n        </Stack.Container>\n    </div>\n\n    <div>\n        <Text is=\"strong\">NEGATIVE</Text>\n\n        <Stack.Container\n            orientation=\"horizontal\"\n            alignment_x=\"stretch\"\n        >\n            <div\n                data-height=\"icon-massive\"\n                style=\"background: hsl(var(--palettes-negative-background-lightest));\"\n            />\n\n            <div\n                data-height=\"icon-massive\"\n                style=\"background: hsl(var(--palettes-negative-background-lighter));\"\n            />\n\n            <div\n                data-height=\"icon-massive\"\n                style=\"background: hsl(var(--palettes-negative-background-light));\"\n            />\n\n            <div\n                data-height=\"icon-massive\"\n                style=\"background: hsl(var(--palettes-negative-background-normal));\"\n            />\n\n            <div\n                data-height=\"icon-massive\"\n                style=\"background: hsl(var(--palettes-negative-background-bold));\"\n            />\n\n            <div\n                data-height=\"icon-massive\"\n                style=\"background: hsl(var(--palettes-negative-background-bolder));\"\n            />\n\n            <div\n                data-height=\"icon-massive\"\n                style=\"background: hsl(var(--palettes-negative-background-boldest));\"\n            />\n        </Stack.Container>\n    </div>\n</Stack.Container>","syntax":"svelte","title":"Palettes Preview"}],"title":"Palettes"},"text":"Palettes IMPORTANT : Palette CSS Custom Properties are defined as a hue, saturation, lightness tuple, so Components can customize opacity based on context. Kahi UI in its default theme uses a simplistic generative palette generator, which mixes the dark and light colors in steps to produce shading. When producing palette shades, the \"lightest\" shade blends in the background the most and \"boldest\" shade stands out of the background the most. With the background palette depending on if the theme is in light or dark mode. In light mode using light as the background, and in dark mode using dark as the background. <script> import {Stack, Text} from \"@kahi-ui/framework\"; </script> <Stack.Container spacing=\"medium\"> <div> <Text is=\"strong\">ACCENT</Text> <Stack.Container orientation=\"horizontal\" alignment_x=\"stretch\" > <div data-height=\"icon-massive\" style=\"background: hsl(var(--palettes-accent-background-lightest));\" /> <div data-height=\"icon-massive\" style=\"background: hsl(var(--palettes-accent-background-lighter));\" /> <div data-height=\"icon-massive\" style=\"background: hsl(var(--palettes-accent-background-light));\" /> <div data-height=\"icon-massive\" style=\"background: hsl(var(--palettes-accent-background-normal));\" /> <div data-height=\"icon-massive\" style=\"background: hsl(var(--palettes-accent-background-bold));\" /> <div data-height=\"icon-massive\" style=\"background: hsl(var(--palettes-accent-background-bolder));\" /> <div data-height=\"icon-massive\" style=\"background: hsl(var(--palettes-accent-background-boldest));\" /> </Stack.Container> </div> <div> <Text is=\"strong\">NEUTRAL</Text> <Stack.Container orientation=\"horizontal\" alignment_x=\"stretch\" > <div data-height=\"icon-massive\" style=\"background: hsl(var(--palettes-neutral-background-lightest));\" /> <div data-height=\"icon-massive\" style=\"background: hsl(var(--palettes-neutral-background-lighter));\" /> <div data-height=\"icon-massive\" style=\"background: hsl(var(--palettes-neutral-background-light));\" /> <div data-height=\"icon-massive\" style=\"background: hsl(var(--palettes-neutral-background-normal));\" /> <div data-height=\"icon-massive\" style=\"background: hsl(var(--palettes-neutral-background-bold));\" /> <div data-height=\"icon-massive\" style=\"background: hsl(var(--palettes-neutral-background-bolder));\" /> <div data-height=\"icon-massive\" style=\"background: hsl(var(--palettes-neutral-background-boldest));\" /> </Stack.Container> </div> <div> <Text is=\"strong\">OFF</Text> <Stack.Container orientation=\"horizontal\" alignment_x=\"stretch\" > <div data-height=\"icon-massive\" style=\"background: hsl(var(--palettes-off-background-lightest));\" /> <div data-height=\"icon-massive\" style=\"background: hsl(var(--palettes-off-background-lighter));\" /> <div data-height=\"icon-massive\" style=\"background: hsl(var(--palettes-off-background-light));\" /> <div data-height=\"icon-massive\" style=\"background: hsl(var(--palettes-off-background-normal));\" /> <div data-height=\"icon-massive\" style=\"background: hsl(var(--palettes-off-background-bold));\" /> <div data-height=\"icon-massive\" style=\"background: hsl(var(--palettes-off-background-bolder));\" /> <div data-height=\"icon-massive\" style=\"background: hsl(var(--palettes-off-background-boldest));\" /> </Stack.Container> </div> <div> <Text is=\"strong\">DARK</Text> <Stack.Container orientation=\"horizontal\" alignment_x=\"stretch\" > <div data-height=\"icon-massive\" style=\"background: hsl(var(--palettes-dark-background-lightest));\" /> <div data-height=\"icon-massive\" style=\"background: hsl(var(--palettes-dark-background-lighter));\" /> <div data-height=\"icon-massive\" style=\"background: hsl(var(--palettes-dark-background-light));\" /> <div data-height=\"icon-massive\" style=\"background: hsl(var(--palettes-dark-background-normal));\" /> <div data-height=\"icon-massive\" style=\"background: hsl(var(--palettes-dark-background-bold));\" /> <div data-height=\"icon-massive\" style=\"background: hsl(var(--palettes-dark-background-bolder));\" /> <div data-height=\"icon-massive\" style=\"background: hsl(var(--palettes-dark-background-boldest));\" /> </Stack.Container> </div> <div> <Text is=\"strong\">LIGHT</Text> <Stack.Container orientation=\"horizontal\" alignment_x=\"stretch\" > <div data-height=\"icon-massive\" style=\"background: hsl(var(--palettes-light-background-lightest));\" /> <div data-height=\"icon-massive\" style=\"background: hsl(var(--palettes-light-background-lighter));\" /> <div data-height=\"icon-massive\" style=\"background: hsl(var(--palettes-light-background-light));\" /> <div data-height=\"icon-massive\" style=\"background: hsl(var(--palettes-light-background-normal));\" /> <div data-height=\"icon-massive\" style=\"background: hsl(var(--palettes-light-background-bold));\" /> <div data-height=\"icon-massive\" style=\"background: hsl(var(--palettes-light-background-bolder));\" /> <div data-height=\"icon-massive\" style=\"background: hsl(var(--palettes-light-background-boldest));\" /> </Stack.Container> </div> <div> <Text is=\"strong\">ALERT</Text> <Stack.Container orientation=\"horizontal\" alignment_x=\"stretch\" > <div data-height=\"icon-massive\" style=\"background: hsl(var(--palettes-alert-background-lightest));\" /> <div data-height=\"icon-massive\" style=\"background: hsl(var(--palettes-alert-background-lighter));\" /> <div data-height=\"icon-massive\" style=\"background: hsl(var(--palettes-alert-background-light));\" /> <div data-height=\"icon-massive\" style=\"background: hsl(var(--palettes-alert-background-normal));\" /> <div data-height=\"icon-massive\" style=\"background: hsl(var(--palettes-alert-background-bold));\" /> <div data-height=\"icon-massive\" style=\"background: hsl(var(--palettes-alert-background-bolder));\" /> <div data-height=\"icon-massive\" style=\"background: hsl(var(--palettes-alert-background-boldest));\" /> </Stack.Container> </div> <div> <Text is=\"strong\">AFFIRMATIVE</Text> <Stack.Container orientation=\"horizontal\" alignment_x=\"stretch\" > <div data-height=\"icon-massive\" style=\"background: hsl(var(--palettes-affirmative-background-lightest));\" /> <div data-height=\"icon-massive\" style=\"background: hsl(var(--palettes-affirmative-background-lighter));\" /> <div data-height=\"icon-massive\" style=\"background: hsl(var(--palettes-affirmative-background-light));\" /> <div data-height=\"icon-massive\" style=\"background: hsl(var(--palettes-affirmative-background-normal));\" /> <div data-height=\"icon-massive\" style=\"background: hsl(var(--palettes-affirmative-background-bold));\" /> <div data-height=\"icon-massive\" style=\"background: hsl(var(--palettes-affirmative-background-bolder));\" /> <div data-height=\"icon-massive\" style=\"background: hsl(var(--palettes-affirmative-background-boldest));\" /> </Stack.Container> </div> <div> <Text is=\"strong\">INFORMATIVE</Text> <Stack.Container orientation=\"horizontal\" alignment_x=\"stretch\" > <div data-height=\"icon-massive\" style=\"background: hsl(var(--palettes-informative-background-lightest));\" /> <div data-height=\"icon-massive\" style=\"background: hsl(var(--palettes-informative-background-lighter));\" /> <div data-height=\"icon-massive\" style=\"background: hsl(var(--palettes-informative-background-light));\" /> <div data-height=\"icon-massive\" style=\"background: hsl(var(--palettes-informative-background-normal));\" /> <div data-height=\"icon-massive\" style=\"background: hsl(var(--palettes-informative-background-bold));\" /> <div data-height=\"icon-massive\" style=\"background: hsl(var(--palettes-informative-background-bolder));\" /> <div data-height=\"icon-massive\" style=\"background: hsl(var(--palettes-informative-background-boldest));\" /> </Stack.Container> </div> <div> <Text is=\"strong\">NEGATIVE</Text> <Stack.Container orientation=\"horizontal\" alignment_x=\"stretch\" > <div data-height=\"icon-massive\" style=\"background: hsl(var(--palettes-negative-background-lightest));\" /> <div data-height=\"icon-massive\" style=\"background: hsl(var(--palettes-negative-background-lighter));\" /> <div data-height=\"icon-massive\" style=\"background: hsl(var(--palettes-negative-background-light));\" /> <div data-height=\"icon-massive\" style=\"background: hsl(var(--palettes-negative-background-normal));\" /> <div data-height=\"icon-massive\" style=\"background: hsl(var(--palettes-negative-background-bold));\" /> <div data-height=\"icon-massive\" style=\"background: hsl(var(--palettes-negative-background-bolder));\" /> <div data-height=\"icon-massive\" style=\"background: hsl(var(--palettes-negative-background-boldest));\" /> </Stack.Container> </div> </Stack.Container> ","references":{"custom_properties":{},"events":{},"properties":{},"slots":{}},"render":"<blockquote data-palette=\"negative\">\n<p><strong>IMPORTANT</strong>: Palette CSS Custom Properties are defined as a <code>hue, saturation, lightness</code> tuple, so Components can customize opacity based on context.</p>\n</blockquote>\n<p>Kahi UI in its <code>default</code> theme uses a simplistic generative palette generator, which mixes the <code>dark</code> and <code>light</code> colors in steps to produce shading.</p>\n<p>When producing palette shades, the &quot;lightest&quot; shade blends in the background the most and &quot;boldest&quot; shade stands out of the background the most. With the background palette depending on if the theme is in light or dark mode. In light mode using <code>light</code> as the background, and in dark mode using <code>dark</code> as the background.</p>\n<pre class=\"highlight language-svelte\" data-identifier=\"palettes-preview\" data-mode=\"repl\" data-syntax=\"svelte\"><code><span class=\"token tag\"><span class=\"token tag\"><span class=\"token punctuation\">&lt;</span>script</span><span class=\"token punctuation\">></span></span><span class=\"token script\"><span class=\"token language-javascript\">\n    <span class=\"token keyword\">import</span> <span class=\"token punctuation\">{</span>Stack<span class=\"token punctuation\">,</span> Text<span class=\"token punctuation\">}</span> <span class=\"token keyword\">from</span> <span class=\"token string\">\"@kahi-ui/framework\"</span><span class=\"token punctuation\">;</span>\n</span></span><span class=\"token tag\"><span class=\"token tag\"><span class=\"token punctuation\">&lt;/</span>script</span><span class=\"token punctuation\">></span></span>\n\n<span class=\"token tag\"><span class=\"token tag\"><span class=\"token punctuation\">&lt;</span>Stack.Container</span> <span class=\"token attr-name\">spacing</span><span class=\"token attr-value\"><span class=\"token punctuation\">=</span><span class=\"token punctuation\">\"</span>medium<span class=\"token punctuation\">\"</span></span><span class=\"token punctuation\">></span></span>\n    <span class=\"token tag\"><span class=\"token tag\"><span class=\"token punctuation\">&lt;</span>div</span><span class=\"token punctuation\">></span></span>\n        <span class=\"token tag\"><span class=\"token tag\"><span class=\"token punctuation\">&lt;</span>Text</span> <span class=\"token attr-name\">is</span><span class=\"token attr-value\"><span class=\"token punctuation\">=</span><span class=\"token punctuation\">\"</span>strong<span class=\"token punctuation\">\"</span></span><span class=\"token punctuation\">></span></span>ACCENT<span class=\"token tag\"><span class=\"token tag\"><span class=\"token punctuation\">&lt;/</span>Text</span><span class=\"token punctuation\">></span></span>\n\n        <span class=\"token tag\"><span class=\"token tag\"><span class=\"token punctuation\">&lt;</span>Stack.Container</span>\n            <span class=\"token attr-name\">orientation</span><span class=\"token attr-value\"><span class=\"token punctuation\">=</span><span class=\"token punctuation\">\"</span>horizontal<span class=\"token punctuation\">\"</span></span>\n            <span class=\"token attr-name\">alignment_x</span><span class=\"token attr-value\"><span class=\"token punctuation\">=</span><span class=\"token punctuation\">\"</span>stretch<span class=\"token punctuation\">\"</span></span>\n        <span class=\"token punctuation\">></span></span>\n            <span class=\"token tag\"><span class=\"token tag\"><span class=\"token punctuation\">&lt;</span>div</span>\n                <span class=\"token attr-name\">data-height</span><span class=\"token attr-value\"><span class=\"token punctuation\">=</span><span class=\"token punctuation\">\"</span>icon-massive<span class=\"token punctuation\">\"</span></span>\n                <span class=\"token attr-name\">style</span><span class=\"token attr-value\"><span class=\"token punctuation\">=</span><span class=\"token punctuation\">\"</span>background: hsl(var(--palettes-accent-background-lightest));<span class=\"token punctuation\">\"</span></span>\n            <span class=\"token punctuation\">/></span></span>\n\n            <span class=\"token tag\"><span class=\"token tag\"><span class=\"token punctuation\">&lt;</span>div</span>\n                <span class=\"token attr-name\">data-height</span><span class=\"token attr-value\"><span class=\"token punctuation\">=</span><span class=\"token punctuation\">\"</span>icon-massive<span class=\"token punctuation\">\"</span></span>\n                <span class=\"token attr-name\">style</span><span class=\"token attr-value\"><span class=\"token punctuation\">=</span><span class=\"token punctuation\">\"</span>background: hsl(var(--palettes-accent-background-lighter));<span class=\"token punctuation\">\"</span></span>\n            <span class=\"token punctuation\">/></span></span>\n\n            <span class=\"token tag\"><span class=\"token tag\"><span class=\"token punctuation\">&lt;</span>div</span>\n                <span class=\"token attr-name\">data-height</span><span class=\"token attr-value\"><span class=\"token punctuation\">=</span><span class=\"token punctuation\">\"</span>icon-massive<span class=\"token punctuation\">\"</span></span>\n                <span class=\"token attr-name\">style</span><span class=\"token attr-value\"><span class=\"token punctuation\">=</span><span class=\"token punctuation\">\"</span>background: hsl(var(--palettes-accent-background-light));<span class=\"token punctuation\">\"</span></span>\n            <span class=\"token punctuation\">/></span></span>\n\n            <span class=\"token tag\"><span class=\"token tag\"><span class=\"token punctuation\">&lt;</span>div</span>\n                <span class=\"token attr-name\">data-height</span><span class=\"token attr-value\"><span class=\"token punctuation\">=</span><span class=\"token punctuation\">\"</span>icon-massive<span class=\"token punctuation\">\"</span></span>\n                <span class=\"token attr-name\">style</span><span class=\"token attr-value\"><span class=\"token punctuation\">=</span><span class=\"token punctuation\">\"</span>background: hsl(var(--palettes-accent-background-normal));<span class=\"token punctuation\">\"</span></span>\n            <span class=\"token punctuation\">/></span></span>\n\n            <span class=\"token tag\"><span class=\"token tag\"><span class=\"token punctuation\">&lt;</span>div</span>\n                <span class=\"token attr-name\">data-height</span><span class=\"token attr-value\"><span class=\"token punctuation\">=</span><span class=\"token punctuation\">\"</span>icon-massive<span class=\"token punctuation\">\"</span></span>\n                <span class=\"token attr-name\">style</span><span class=\"token attr-value\"><span class=\"token punctuation\">=</span><span class=\"token punctuation\">\"</span>background: hsl(var(--palettes-accent-background-bold));<span class=\"token punctuation\">\"</span></span>\n            <span class=\"token punctuation\">/></span></span>\n\n            <span class=\"token tag\"><span class=\"token tag\"><span class=\"token punctuation\">&lt;</span>div</span>\n                <span class=\"token attr-name\">data-height</span><span class=\"token attr-value\"><span class=\"token punctuation\">=</span><span class=\"token punctuation\">\"</span>icon-massive<span class=\"token punctuation\">\"</span></span>\n                <span class=\"token attr-name\">style</span><span class=\"token attr-value\"><span class=\"token punctuation\">=</span><span class=\"token punctuation\">\"</span>background: hsl(var(--palettes-accent-background-bolder));<span class=\"token punctuation\">\"</span></span>\n            <span class=\"token punctuation\">/></span></span>\n\n            <span class=\"token tag\"><span class=\"token tag\"><span class=\"token punctuation\">&lt;</span>div</span>\n                <span class=\"token attr-name\">data-height</span><span class=\"token attr-value\"><span class=\"token punctuation\">=</span><span class=\"token punctuation\">\"</span>icon-massive<span class=\"token punctuation\">\"</span></span>\n                <span class=\"token attr-name\">style</span><span class=\"token attr-value\"><span class=\"token punctuation\">=</span><span class=\"token punctuation\">\"</span>background: hsl(var(--palettes-accent-background-boldest));<span class=\"token punctuation\">\"</span></span>\n            <span class=\"token punctuation\">/></span></span>\n        <span class=\"token tag\"><span class=\"token tag\"><span class=\"token punctuation\">&lt;/</span>Stack.Container</span><span class=\"token punctuation\">></span></span>\n    <span class=\"token tag\"><span class=\"token tag\"><span class=\"token punctuation\">&lt;/</span>div</span><span class=\"token punctuation\">></span></span>\n\n    <span class=\"token tag\"><span class=\"token tag\"><span class=\"token punctuation\">&lt;</span>div</span><span class=\"token punctuation\">></span></span>\n        <span class=\"token tag\"><span class=\"token tag\"><span class=\"token punctuation\">&lt;</span>Text</span> <span class=\"token attr-name\">is</span><span class=\"token attr-value\"><span class=\"token punctuation\">=</span><span class=\"token punctuation\">\"</span>strong<span class=\"token punctuation\">\"</span></span><span class=\"token punctuation\">></span></span>NEUTRAL<span class=\"token tag\"><span class=\"token tag\"><span class=\"token punctuation\">&lt;/</span>Text</span><span class=\"token punctuation\">></span></span>\n\n        <span class=\"token tag\"><span class=\"token tag\"><span class=\"token punctuation\">&lt;</span>Stack.Container</span>\n            <span class=\"token attr-name\">orientation</span><span class=\"token attr-value\"><span class=\"token punctuation\">=</span><span class=\"token punctuation\">\"</span>horizontal<span class=\"token punctuation\">\"</span></span>\n            <span class=\"token attr-name\">alignment_x</span><span class=\"token attr-value\"><span class=\"token punctuation\">=</span><span class=\"token punctuation\">\"</span>stretch<span class=\"token punctuation\">\"</span></span>\n        <span class=\"token punctuation\">></span></span>\n            <span class=\"token tag\"><span class=\"token tag\"><span class=\"token punctuation\">&lt;</span>div</span>\n                <span class=\"token attr-name\">data-height</span><span class=\"token attr-value\"><span class=\"token punctuation\">=</span><span class=\"token punctuation\">\"</span>icon-massive<span class=\"token punctuation\">\"</span></span>\n                <span class=\"token attr-name\">style</span><span class=\"token attr-value\"><span class=\"token punctuation\">=</span><span class=\"token punctuation\">\"</span>background: hsl(var(--palettes-neutral-background-lightest));<span class=\"token punctuation\">\"</span></span>\n            <span class=\"token punctuation\">/></span></span>\n\n            <span class=\"token tag\"><span class=\"token tag\"><span class=\"token punctuation\">&lt;</span>div</span>\n                <span class=\"token attr-name\">data-height</span><span class=\"token attr-value\"><span class=\"token punctuation\">=</span><span class=\"token punctuation\">\"</span>icon-massive<span class=\"token punctuation\">\"</span></span>\n                <span class=\"token attr-name\">style</span><span class=\"token attr-value\"><span class=\"token punctuation\">=</span><span class=\"token punctuation\">\"</span>background: hsl(var(--palettes-neutral-background-lighter));<span class=\"token punctuation\">\"</span></span>\n            <span class=\"token punctuation\">/></span></span>\n\n            <span class=\"token tag\"><span class=\"token tag\"><span class=\"token punctuation\">&lt;</span>div</span>\n                <span class=\"token attr-name\">data-height</span><span class=\"token attr-value\"><span class=\"token punctuation\">=</span><span class=\"token punctuation\">\"</span>icon-massive<span class=\"token punctuation\">\"</span></span>\n                <span class=\"token attr-name\">style</span><span class=\"token attr-value\"><span class=\"token punctuation\">=</span><span class=\"token punctuation\">\"</span>background: hsl(var(--palettes-neutral-background-light));<span class=\"token punctuation\">\"</span></span>\n            <span class=\"token punctuation\">/></span></span>\n\n            <span class=\"token tag\"><span class=\"token tag\"><span class=\"token punctuation\">&lt;</span>div</span>\n                <span class=\"token attr-name\">data-height</span><span class=\"token attr-value\"><span class=\"token punctuation\">=</span><span class=\"token punctuation\">\"</span>icon-massive<span class=\"token punctuation\">\"</span></span>\n                <span class=\"token attr-name\">style</span><span class=\"token attr-value\"><span class=\"token punctuation\">=</span><span class=\"token punctuation\">\"</span>background: hsl(var(--palettes-neutral-background-normal));<span class=\"token punctuation\">\"</span></span>\n            <span class=\"token punctuation\">/></span></span>\n\n            <span class=\"token tag\"><span class=\"token tag\"><span class=\"token punctuation\">&lt;</span>div</span>\n                <span class=\"token attr-name\">data-height</span><span class=\"token attr-value\"><span class=\"token punctuation\">=</span><span class=\"token punctuation\">\"</span>icon-massive<span class=\"token punctuation\">\"</span></span>\n                <span class=\"token attr-name\">style</span><span class=\"token attr-value\"><span class=\"token punctuation\">=</span><span class=\"token punctuation\">\"</span>background: hsl(var(--palettes-neutral-background-bold));<span class=\"token punctuation\">\"</span></span>\n            <span class=\"token punctuation\">/></span></span>\n\n            <span class=\"token tag\"><span class=\"token tag\"><span class=\"token punctuation\">&lt;</span>div</span>\n                <span class=\"token attr-name\">data-height</span><span class=\"token attr-value\"><span class=\"token punctuation\">=</span><span class=\"token punctuation\">\"</span>icon-massive<span class=\"token punctuation\">\"</span></span>\n                <span class=\"token attr-name\">style</span><span class=\"token attr-value\"><span class=\"token punctuation\">=</span><span class=\"token punctuation\">\"</span>background: hsl(var(--palettes-neutral-background-bolder));<span class=\"token punctuation\">\"</span></span>\n            <span class=\"token punctuation\">/></span></span>\n\n            <span class=\"token tag\"><span class=\"token tag\"><span class=\"token punctuation\">&lt;</span>div</span>\n                <span class=\"token attr-name\">data-height</span><span class=\"token attr-value\"><span class=\"token punctuation\">=</span><span class=\"token punctuation\">\"</span>icon-massive<span class=\"token punctuation\">\"</span></span>\n                <span class=\"token attr-name\">style</span><span class=\"token attr-value\"><span class=\"token punctuation\">=</span><span class=\"token punctuation\">\"</span>background: hsl(var(--palettes-neutral-background-boldest));<span class=\"token punctuation\">\"</span></span>\n            <span class=\"token punctuation\">/></span></span>\n        <span class=\"token tag\"><span class=\"token tag\"><span class=\"token punctuation\">&lt;/</span>Stack.Container</span><span class=\"token punctuation\">></span></span>\n    <span class=\"token tag\"><span class=\"token tag\"><span class=\"token punctuation\">&lt;/</span>div</span><span class=\"token punctuation\">></span></span>\n\n    <span class=\"token tag\"><span class=\"token tag\"><span class=\"token punctuation\">&lt;</span>div</span><span class=\"token punctuation\">></span></span>\n        <span class=\"token tag\"><span class=\"token tag\"><span class=\"token punctuation\">&lt;</span>Text</span> <span class=\"token attr-name\">is</span><span class=\"token attr-value\"><span class=\"token punctuation\">=</span><span class=\"token punctuation\">\"</span>strong<span class=\"token punctuation\">\"</span></span><span class=\"token punctuation\">></span></span>OFF<span class=\"token tag\"><span class=\"token tag\"><span class=\"token punctuation\">&lt;/</span>Text</span><span class=\"token punctuation\">></span></span>\n\n        <span class=\"token tag\"><span class=\"token tag\"><span class=\"token punctuation\">&lt;</span>Stack.Container</span>\n            <span class=\"token attr-name\">orientation</span><span class=\"token attr-value\"><span class=\"token punctuation\">=</span><span class=\"token punctuation\">\"</span>horizontal<span class=\"token punctuation\">\"</span></span>\n            <span class=\"token attr-name\">alignment_x</span><span class=\"token attr-value\"><span class=\"token punctuation\">=</span><span class=\"token punctuation\">\"</span>stretch<span class=\"token punctuation\">\"</span></span>\n        <span class=\"token punctuation\">></span></span>\n            <span class=\"token tag\"><span class=\"token tag\"><span class=\"token punctuation\">&lt;</span>div</span>\n                <span class=\"token attr-name\">data-height</span><span class=\"token attr-value\"><span class=\"token punctuation\">=</span><span class=\"token punctuation\">\"</span>icon-massive<span class=\"token punctuation\">\"</span></span>\n                <span class=\"token attr-name\">style</span><span class=\"token attr-value\"><span class=\"token punctuation\">=</span><span class=\"token punctuation\">\"</span>background: hsl(var(--palettes-off-background-lightest));<span class=\"token punctuation\">\"</span></span>\n            <span class=\"token punctuation\">/></span></span>\n\n            <span class=\"token tag\"><span class=\"token tag\"><span class=\"token punctuation\">&lt;</span>div</span>\n                <span class=\"token attr-name\">data-height</span><span class=\"token attr-value\"><span class=\"token punctuation\">=</span><span class=\"token punctuation\">\"</span>icon-massive<span class=\"token punctuation\">\"</span></span>\n                <span class=\"token attr-name\">style</span><span class=\"token attr-value\"><span class=\"token punctuation\">=</span><span class=\"token punctuation\">\"</span>background: hsl(var(--palettes-off-background-lighter));<span class=\"token punctuation\">\"</span></span>\n            <span class=\"token punctuation\">/></span></span>\n\n            <span class=\"token tag\"><span class=\"token tag\"><span class=\"token punctuation\">&lt;</span>div</span>\n                <span class=\"token attr-name\">data-height</span><span class=\"token attr-value\"><span class=\"token punctuation\">=</span><span class=\"token punctuation\">\"</span>icon-massive<span class=\"token punctuation\">\"</span></span>\n                <span class=\"token attr-name\">style</span><span class=\"token attr-value\"><span class=\"token punctuation\">=</span><span class=\"token punctuation\">\"</span>background: hsl(var(--palettes-off-background-light));<span class=\"token punctuation\">\"</span></span>\n            <span class=\"token punctuation\">/></span></span>\n\n            <span class=\"token tag\"><span class=\"token tag\"><span class=\"token punctuation\">&lt;</span>div</span>\n                <span class=\"token attr-name\">data-height</span><span class=\"token attr-value\"><span class=\"token punctuation\">=</span><span class=\"token punctuation\">\"</span>icon-massive<span class=\"token punctuation\">\"</span></span>\n                <span class=\"token attr-name\">style</span><span class=\"token attr-value\"><span class=\"token punctuation\">=</span><span class=\"token punctuation\">\"</span>background: hsl(var(--palettes-off-background-normal));<span class=\"token punctuation\">\"</span></span>\n            <span class=\"token punctuation\">/></span></span>\n\n            <span class=\"token tag\"><span class=\"token tag\"><span class=\"token punctuation\">&lt;</span>div</span>\n                <span class=\"token attr-name\">data-height</span><span class=\"token attr-value\"><span class=\"token punctuation\">=</span><span class=\"token punctuation\">\"</span>icon-massive<span class=\"token punctuation\">\"</span></span>\n                <span class=\"token attr-name\">style</span><span class=\"token attr-value\"><span class=\"token punctuation\">=</span><span class=\"token punctuation\">\"</span>background: hsl(var(--palettes-off-background-bold));<span class=\"token punctuation\">\"</span></span>\n            <span class=\"token punctuation\">/></span></span>\n\n            <span class=\"token tag\"><span class=\"token tag\"><span class=\"token punctuation\">&lt;</span>div</span>\n                <span class=\"token attr-name\">data-height</span><span class=\"token attr-value\"><span class=\"token punctuation\">=</span><span class=\"token punctuation\">\"</span>icon-massive<span class=\"token punctuation\">\"</span></span>\n                <span class=\"token attr-name\">style</span><span class=\"token attr-value\"><span class=\"token punctuation\">=</span><span class=\"token punctuation\">\"</span>background: hsl(var(--palettes-off-background-bolder));<span class=\"token punctuation\">\"</span></span>\n            <span class=\"token punctuation\">/></span></span>\n\n            <span class=\"token tag\"><span class=\"token tag\"><span class=\"token punctuation\">&lt;</span>div</span>\n                <span class=\"token attr-name\">data-height</span><span class=\"token attr-value\"><span class=\"token punctuation\">=</span><span class=\"token punctuation\">\"</span>icon-massive<span class=\"token punctuation\">\"</span></span>\n                <span class=\"token attr-name\">style</span><span class=\"token attr-value\"><span class=\"token punctuation\">=</span><span class=\"token punctuation\">\"</span>background: hsl(var(--palettes-off-background-boldest));<span class=\"token punctuation\">\"</span></span>\n            <span class=\"token punctuation\">/></span></span>\n        <span class=\"token tag\"><span class=\"token tag\"><span class=\"token punctuation\">&lt;/</span>Stack.Container</span><span class=\"token punctuation\">></span></span>\n    <span class=\"token tag\"><span class=\"token tag\"><span class=\"token punctuation\">&lt;/</span>div</span><span class=\"token punctuation\">></span></span>\n\n    <span class=\"token tag\"><span class=\"token tag\"><span class=\"token punctuation\">&lt;</span>div</span><span class=\"token punctuation\">></span></span>\n        <span class=\"token tag\"><span class=\"token tag\"><span class=\"token punctuation\">&lt;</span>Text</span> <span class=\"token attr-name\">is</span><span class=\"token attr-value\"><span class=\"token punctuation\">=</span><span class=\"token punctuation\">\"</span>strong<span class=\"token punctuation\">\"</span></span><span class=\"token punctuation\">></span></span>DARK<span class=\"token tag\"><span class=\"token tag\"><span class=\"token punctuation\">&lt;/</span>Text</span><span class=\"token punctuation\">></span></span>\n\n        <span class=\"token tag\"><span class=\"token tag\"><span class=\"token punctuation\">&lt;</span>Stack.Container</span>\n            <span class=\"token attr-name\">orientation</span><span class=\"token attr-value\"><span class=\"token punctuation\">=</span><span class=\"token punctuation\">\"</span>horizontal<span class=\"token punctuation\">\"</span></span>\n            <span class=\"token attr-name\">alignment_x</span><span class=\"token attr-value\"><span class=\"token punctuation\">=</span><span class=\"token punctuation\">\"</span>stretch<span class=\"token punctuation\">\"</span></span>\n        <span class=\"token punctuation\">></span></span>\n            <span class=\"token tag\"><span class=\"token tag\"><span class=\"token punctuation\">&lt;</span>div</span>\n                <span class=\"token attr-name\">data-height</span><span class=\"token attr-value\"><span class=\"token punctuation\">=</span><span class=\"token punctuation\">\"</span>icon-massive<span class=\"token punctuation\">\"</span></span>\n                <span class=\"token attr-name\">style</span><span class=\"token attr-value\"><span class=\"token punctuation\">=</span><span class=\"token punctuation\">\"</span>background: hsl(var(--palettes-dark-background-lightest));<span class=\"token punctuation\">\"</span></span>\n            <span class=\"token punctuation\">/></span></span>\n\n            <span class=\"token tag\"><span class=\"token tag\"><span class=\"token punctuation\">&lt;</span>div</span>\n                <span class=\"token attr-name\">data-height</span><span class=\"token attr-value\"><span class=\"token punctuation\">=</span><span class=\"token punctuation\">\"</span>icon-massive<span class=\"token punctuation\">\"</span></span>\n                <span class=\"token attr-name\">style</span><span class=\"token attr-value\"><span class=\"token punctuation\">=</span><span class=\"token punctuation\">\"</span>background: hsl(var(--palettes-dark-background-lighter));<span class=\"token punctuation\">\"</span></span>\n            <span class=\"token punctuation\">/></span></span>\n\n            <span class=\"token tag\"><span class=\"token tag\"><span class=\"token punctuation\">&lt;</span>div</span>\n                <span class=\"token attr-name\">data-height</span><span class=\"token attr-value\"><span class=\"token punctuation\">=</span><span class=\"token punctuation\">\"</span>icon-massive<span class=\"token punctuation\">\"</span></span>\n                <span class=\"token attr-name\">style</span><span class=\"token attr-value\"><span class=\"token punctuation\">=</span><span class=\"token punctuation\">\"</span>background: hsl(var(--palettes-dark-background-light));<span class=\"token punctuation\">\"</span></span>\n            <span class=\"token punctuation\">/></span></span>\n\n            <span class=\"token tag\"><span class=\"token tag\"><span class=\"token punctuation\">&lt;</span>div</span>\n                <span class=\"token attr-name\">data-height</span><span class=\"token attr-value\"><span class=\"token punctuation\">=</span><span class=\"token punctuation\">\"</span>icon-massive<span class=\"token punctuation\">\"</span></span>\n                <span class=\"token attr-name\">style</span><span class=\"token attr-value\"><span class=\"token punctuation\">=</span><span class=\"token punctuation\">\"</span>background: hsl(var(--palettes-dark-background-normal));<span class=\"token punctuation\">\"</span></span>\n            <span class=\"token punctuation\">/></span></span>\n\n            <span class=\"token tag\"><span class=\"token tag\"><span class=\"token punctuation\">&lt;</span>div</span>\n                <span class=\"token attr-name\">data-height</span><span class=\"token attr-value\"><span class=\"token punctuation\">=</span><span class=\"token punctuation\">\"</span>icon-massive<span class=\"token punctuation\">\"</span></span>\n                <span class=\"token attr-name\">style</span><span class=\"token attr-value\"><span class=\"token punctuation\">=</span><span class=\"token punctuation\">\"</span>background: hsl(var(--palettes-dark-background-bold));<span class=\"token punctuation\">\"</span></span>\n            <span class=\"token punctuation\">/></span></span>\n\n            <span class=\"token tag\"><span class=\"token tag\"><span class=\"token punctuation\">&lt;</span>div</span>\n                <span class=\"token attr-name\">data-height</span><span class=\"token attr-value\"><span class=\"token punctuation\">=</span><span class=\"token punctuation\">\"</span>icon-massive<span class=\"token punctuation\">\"</span></span>\n                <span class=\"token attr-name\">style</span><span class=\"token attr-value\"><span class=\"token punctuation\">=</span><span class=\"token punctuation\">\"</span>background: hsl(var(--palettes-dark-background-bolder));<span class=\"token punctuation\">\"</span></span>\n            <span class=\"token punctuation\">/></span></span>\n\n            <span class=\"token tag\"><span class=\"token tag\"><span class=\"token punctuation\">&lt;</span>div</span>\n                <span class=\"token attr-name\">data-height</span><span class=\"token attr-value\"><span class=\"token punctuation\">=</span><span class=\"token punctuation\">\"</span>icon-massive<span class=\"token punctuation\">\"</span></span>\n                <span class=\"token attr-name\">style</span><span class=\"token attr-value\"><span class=\"token punctuation\">=</span><span class=\"token punctuation\">\"</span>background: hsl(var(--palettes-dark-background-boldest));<span class=\"token punctuation\">\"</span></span>\n            <span class=\"token punctuation\">/></span></span>\n        <span class=\"token tag\"><span class=\"token tag\"><span class=\"token punctuation\">&lt;/</span>Stack.Container</span><span class=\"token punctuation\">></span></span>\n    <span class=\"token tag\"><span class=\"token tag\"><span class=\"token punctuation\">&lt;/</span>div</span><span class=\"token punctuation\">></span></span>\n\n    <span class=\"token tag\"><span class=\"token tag\"><span class=\"token punctuation\">&lt;</span>div</span><span class=\"token punctuation\">></span></span>\n        <span class=\"token tag\"><span class=\"token tag\"><span class=\"token punctuation\">&lt;</span>Text</span> <span class=\"token attr-name\">is</span><span class=\"token attr-value\"><span class=\"token punctuation\">=</span><span class=\"token punctuation\">\"</span>strong<span class=\"token punctuation\">\"</span></span><span class=\"token punctuation\">></span></span>LIGHT<span class=\"token tag\"><span class=\"token tag\"><span class=\"token punctuation\">&lt;/</span>Text</span><span class=\"token punctuation\">></span></span>\n\n        <span class=\"token tag\"><span class=\"token tag\"><span class=\"token punctuation\">&lt;</span>Stack.Container</span>\n            <span class=\"token attr-name\">orientation</span><span class=\"token attr-value\"><span class=\"token punctuation\">=</span><span class=\"token punctuation\">\"</span>horizontal<span class=\"token punctuation\">\"</span></span>\n            <span class=\"token attr-name\">alignment_x</span><span class=\"token attr-value\"><span class=\"token punctuation\">=</span><span class=\"token punctuation\">\"</span>stretch<span class=\"token punctuation\">\"</span></span>\n        <span class=\"token punctuation\">></span></span>\n            <span class=\"token tag\"><span class=\"token tag\"><span class=\"token punctuation\">&lt;</span>div</span>\n                <span class=\"token attr-name\">data-height</span><span class=\"token attr-value\"><span class=\"token punctuation\">=</span><span class=\"token punctuation\">\"</span>icon-massive<span class=\"token punctuation\">\"</span></span>\n                <span class=\"token attr-name\">style</span><span class=\"token attr-value\"><span class=\"token punctuation\">=</span><span class=\"token punctuation\">\"</span>background: hsl(var(--palettes-light-background-lightest));<span class=\"token punctuation\">\"</span></span>\n            <span class=\"token punctuation\">/></span></span>\n\n            <span class=\"token tag\"><span class=\"token tag\"><span class=\"token punctuation\">&lt;</span>div</span>\n                <span class=\"token attr-name\">data-height</span><span class=\"token attr-value\"><span class=\"token punctuation\">=</span><span class=\"token punctuation\">\"</span>icon-massive<span class=\"token punctuation\">\"</span></span>\n                <span class=\"token attr-name\">style</span><span class=\"token attr-value\"><span class=\"token punctuation\">=</span><span class=\"token punctuation\">\"</span>background: hsl(var(--palettes-light-background-lighter));<span class=\"token punctuation\">\"</span></span>\n            <span class=\"token punctuation\">/></span></span>\n\n            <span class=\"token tag\"><span class=\"token tag\"><span class=\"token punctuation\">&lt;</span>div</span>\n                <span class=\"token attr-name\">data-height</span><span class=\"token attr-value\"><span class=\"token punctuation\">=</span><span class=\"token punctuation\">\"</span>icon-massive<span class=\"token punctuation\">\"</span></span>\n                <span class=\"token attr-name\">style</span><span class=\"token attr-value\"><span class=\"token punctuation\">=</span><span class=\"token punctuation\">\"</span>background: hsl(var(--palettes-light-background-light));<span class=\"token punctuation\">\"</span></span>\n            <span class=\"token punctuation\">/></span></span>\n\n            <span class=\"token tag\"><span class=\"token tag\"><span class=\"token punctuation\">&lt;</span>div</span>\n                <span class=\"token attr-name\">data-height</span><span class=\"token attr-value\"><span class=\"token punctuation\">=</span><span class=\"token punctuation\">\"</span>icon-massive<span class=\"token punctuation\">\"</span></span>\n                <span class=\"token attr-name\">style</span><span class=\"token attr-value\"><span class=\"token punctuation\">=</span><span class=\"token punctuation\">\"</span>background: hsl(var(--palettes-light-background-normal));<span class=\"token punctuation\">\"</span></span>\n            <span class=\"token punctuation\">/></span></span>\n\n            <span class=\"token tag\"><span class=\"token tag\"><span class=\"token punctuation\">&lt;</span>div</span>\n                <span class=\"token attr-name\">data-height</span><span class=\"token attr-value\"><span class=\"token punctuation\">=</span><span class=\"token punctuation\">\"</span>icon-massive<span class=\"token punctuation\">\"</span></span>\n                <span class=\"token attr-name\">style</span><span class=\"token attr-value\"><span class=\"token punctuation\">=</span><span class=\"token punctuation\">\"</span>background: hsl(var(--palettes-light-background-bold));<span class=\"token punctuation\">\"</span></span>\n            <span class=\"token punctuation\">/></span></span>\n\n            <span class=\"token tag\"><span class=\"token tag\"><span class=\"token punctuation\">&lt;</span>div</span>\n                <span class=\"token attr-name\">data-height</span><span class=\"token attr-value\"><span class=\"token punctuation\">=</span><span class=\"token punctuation\">\"</span>icon-massive<span class=\"token punctuation\">\"</span></span>\n                <span class=\"token attr-name\">style</span><span class=\"token attr-value\"><span class=\"token punctuation\">=</span><span class=\"token punctuation\">\"</span>background: hsl(var(--palettes-light-background-bolder));<span class=\"token punctuation\">\"</span></span>\n            <span class=\"token punctuation\">/></span></span>\n\n            <span class=\"token tag\"><span class=\"token tag\"><span class=\"token punctuation\">&lt;</span>div</span>\n                <span class=\"token attr-name\">data-height</span><span class=\"token attr-value\"><span class=\"token punctuation\">=</span><span class=\"token punctuation\">\"</span>icon-massive<span class=\"token punctuation\">\"</span></span>\n                <span class=\"token attr-name\">style</span><span class=\"token attr-value\"><span class=\"token punctuation\">=</span><span class=\"token punctuation\">\"</span>background: hsl(var(--palettes-light-background-boldest));<span class=\"token punctuation\">\"</span></span>\n            <span class=\"token punctuation\">/></span></span>\n        <span class=\"token tag\"><span class=\"token tag\"><span class=\"token punctuation\">&lt;/</span>Stack.Container</span><span class=\"token punctuation\">></span></span>\n    <span class=\"token tag\"><span class=\"token tag\"><span class=\"token punctuation\">&lt;/</span>div</span><span class=\"token punctuation\">></span></span>\n\n    <span class=\"token tag\"><span class=\"token tag\"><span class=\"token punctuation\">&lt;</span>div</span><span class=\"token punctuation\">></span></span>\n        <span class=\"token tag\"><span class=\"token tag\"><span class=\"token punctuation\">&lt;</span>Text</span> <span class=\"token attr-name\">is</span><span class=\"token attr-value\"><span class=\"token punctuation\">=</span><span class=\"token punctuation\">\"</span>strong<span class=\"token punctuation\">\"</span></span><span class=\"token punctuation\">></span></span>ALERT<span class=\"token tag\"><span class=\"token tag\"><span class=\"token punctuation\">&lt;/</span>Text</span><span class=\"token punctuation\">></span></span>\n\n        <span class=\"token tag\"><span class=\"token tag\"><span class=\"token punctuation\">&lt;</span>Stack.Container</span>\n            <span class=\"token attr-name\">orientation</span><span class=\"token attr-value\"><span class=\"token punctuation\">=</span><span class=\"token punctuation\">\"</span>horizontal<span class=\"token punctuation\">\"</span></span>\n            <span class=\"token attr-name\">alignment_x</span><span class=\"token attr-value\"><span class=\"token punctuation\">=</span><span class=\"token punctuation\">\"</span>stretch<span class=\"token punctuation\">\"</span></span>\n        <span class=\"token punctuation\">></span></span>\n            <span class=\"token tag\"><span class=\"token tag\"><span class=\"token punctuation\">&lt;</span>div</span>\n                <span class=\"token attr-name\">data-height</span><span class=\"token attr-value\"><span class=\"token punctuation\">=</span><span class=\"token punctuation\">\"</span>icon-massive<span class=\"token punctuation\">\"</span></span>\n                <span class=\"token attr-name\">style</span><span class=\"token attr-value\"><span class=\"token punctuation\">=</span><span class=\"token punctuation\">\"</span>background: hsl(var(--palettes-alert-background-lightest));<span class=\"token punctuation\">\"</span></span>\n            <span class=\"token punctuation\">/></span></span>\n\n            <span class=\"token tag\"><span class=\"token tag\"><span class=\"token punctuation\">&lt;</span>div</span>\n                <span class=\"token attr-name\">data-height</span><span class=\"token attr-value\"><span class=\"token punctuation\">=</span><span class=\"token punctuation\">\"</span>icon-massive<span class=\"token punctuation\">\"</span></span>\n                <span class=\"token attr-name\">style</span><span class=\"token attr-value\"><span class=\"token punctuation\">=</span><span class=\"token punctuation\">\"</span>background: hsl(var(--palettes-alert-background-lighter));<span class=\"token punctuation\">\"</span></span>\n            <span class=\"token punctuation\">/></span></span>\n\n            <span class=\"token tag\"><span class=\"token tag\"><span class=\"token punctuation\">&lt;</span>div</span>\n                <span class=\"token attr-name\">data-height</span><span class=\"token attr-value\"><span class=\"token punctuation\">=</span><span class=\"token punctuation\">\"</span>icon-massive<span class=\"token punctuation\">\"</span></span>\n                <span class=\"token attr-name\">style</span><span class=\"token attr-value\"><span class=\"token punctuation\">=</span><span class=\"token punctuation\">\"</span>background: hsl(var(--palettes-alert-background-light));<span class=\"token punctuation\">\"</span></span>\n            <span class=\"token punctuation\">/></span></span>\n\n            <span class=\"token tag\"><span class=\"token tag\"><span class=\"token punctuation\">&lt;</span>div</span>\n                <span class=\"token attr-name\">data-height</span><span class=\"token attr-value\"><span class=\"token punctuation\">=</span><span class=\"token punctuation\">\"</span>icon-massive<span class=\"token punctuation\">\"</span></span>\n                <span class=\"token attr-name\">style</span><span class=\"token attr-value\"><span class=\"token punctuation\">=</span><span class=\"token punctuation\">\"</span>background: hsl(var(--palettes-alert-background-normal));<span class=\"token punctuation\">\"</span></span>\n            <span class=\"token punctuation\">/></span></span>\n\n            <span class=\"token tag\"><span class=\"token tag\"><span class=\"token punctuation\">&lt;</span>div</span>\n                <span class=\"token attr-name\">data-height</span><span class=\"token attr-value\"><span class=\"token punctuation\">=</span><span class=\"token punctuation\">\"</span>icon-massive<span class=\"token punctuation\">\"</span></span>\n                <span class=\"token attr-name\">style</span><span class=\"token attr-value\"><span class=\"token punctuation\">=</span><span class=\"token punctuation\">\"</span>background: hsl(var(--palettes-alert-background-bold));<span class=\"token punctuation\">\"</span></span>\n            <span class=\"token punctuation\">/></span></span>\n\n            <span class=\"token tag\"><span class=\"token tag\"><span class=\"token punctuation\">&lt;</span>div</span>\n                <span class=\"token attr-name\">data-height</span><span class=\"token attr-value\"><span class=\"token punctuation\">=</span><span class=\"token punctuation\">\"</span>icon-massive<span class=\"token punctuation\">\"</span></span>\n                <span class=\"token attr-name\">style</span><span class=\"token attr-value\"><span class=\"token punctuation\">=</span><span class=\"token punctuation\">\"</span>background: hsl(var(--palettes-alert-background-bolder));<span class=\"token punctuation\">\"</span></span>\n            <span class=\"token punctuation\">/></span></span>\n\n            <span class=\"token tag\"><span class=\"token tag\"><span class=\"token punctuation\">&lt;</span>div</span>\n                <span class=\"token attr-name\">data-height</span><span class=\"token attr-value\"><span class=\"token punctuation\">=</span><span class=\"token punctuation\">\"</span>icon-massive<span class=\"token punctuation\">\"</span></span>\n                <span class=\"token attr-name\">style</span><span class=\"token attr-value\"><span class=\"token punctuation\">=</span><span class=\"token punctuation\">\"</span>background: hsl(var(--palettes-alert-background-boldest));<span class=\"token punctuation\">\"</span></span>\n            <span class=\"token punctuation\">/></span></span>\n        <span class=\"token tag\"><span class=\"token tag\"><span class=\"token punctuation\">&lt;/</span>Stack.Container</span><span class=\"token punctuation\">></span></span>\n    <span class=\"token tag\"><span class=\"token tag\"><span class=\"token punctuation\">&lt;/</span>div</span><span class=\"token punctuation\">></span></span>\n\n    <span class=\"token tag\"><span class=\"token tag\"><span class=\"token punctuation\">&lt;</span>div</span><span class=\"token punctuation\">></span></span>\n        <span class=\"token tag\"><span class=\"token tag\"><span class=\"token punctuation\">&lt;</span>Text</span> <span class=\"token attr-name\">is</span><span class=\"token attr-value\"><span class=\"token punctuation\">=</span><span class=\"token punctuation\">\"</span>strong<span class=\"token punctuation\">\"</span></span><span class=\"token punctuation\">></span></span>AFFIRMATIVE<span class=\"token tag\"><span class=\"token tag\"><span class=\"token punctuation\">&lt;/</span>Text</span><span class=\"token punctuation\">></span></span>\n\n        <span class=\"token tag\"><span class=\"token tag\"><span class=\"token punctuation\">&lt;</span>Stack.Container</span>\n            <span class=\"token attr-name\">orientation</span><span class=\"token attr-value\"><span class=\"token punctuation\">=</span><span class=\"token punctuation\">\"</span>horizontal<span class=\"token punctuation\">\"</span></span>\n            <span class=\"token attr-name\">alignment_x</span><span class=\"token attr-value\"><span class=\"token punctuation\">=</span><span class=\"token punctuation\">\"</span>stretch<span class=\"token punctuation\">\"</span></span>\n        <span class=\"token punctuation\">></span></span>\n            <span class=\"token tag\"><span class=\"token tag\"><span class=\"token punctuation\">&lt;</span>div</span>\n                <span class=\"token attr-name\">data-height</span><span class=\"token attr-value\"><span class=\"token punctuation\">=</span><span class=\"token punctuation\">\"</span>icon-massive<span class=\"token punctuation\">\"</span></span>\n                <span class=\"token attr-name\">style</span><span class=\"token attr-value\"><span class=\"token punctuation\">=</span><span class=\"token punctuation\">\"</span>background: hsl(var(--palettes-affirmative-background-lightest));<span class=\"token punctuation\">\"</span></span>\n            <span class=\"token punctuation\">/></span></span>\n\n            <span class=\"token tag\"><span class=\"token tag\"><span class=\"token punctuation\">&lt;</span>div</span>\n                <span class=\"token attr-name\">data-height</span><span class=\"token attr-value\"><span class=\"token punctuation\">=</span><span class=\"token punctuation\">\"</span>icon-massive<span class=\"token punctuation\">\"</span></span>\n                <span class=\"token attr-name\">style</span><span class=\"token attr-value\"><span class=\"token punctuation\">=</span><span class=\"token punctuation\">\"</span>background: hsl(var(--palettes-affirmative-background-lighter));<span class=\"token punctuation\">\"</span></span>\n            <span class=\"token punctuation\">/></span></span>\n\n            <span class=\"token tag\"><span class=\"token tag\"><span class=\"token punctuation\">&lt;</span>div</span>\n                <span class=\"token attr-name\">data-height</span><span class=\"token attr-value\"><span class=\"token punctuation\">=</span><span class=\"token punctuation\">\"</span>icon-massive<span class=\"token punctuation\">\"</span></span>\n                <span class=\"token attr-name\">style</span><span class=\"token attr-value\"><span class=\"token punctuation\">=</span><span class=\"token punctuation\">\"</span>background: hsl(var(--palettes-affirmative-background-light));<span class=\"token punctuation\">\"</span></span>\n            <span class=\"token punctuation\">/></span></span>\n\n            <span class=\"token tag\"><span class=\"token tag\"><span class=\"token punctuation\">&lt;</span>div</span>\n                <span class=\"token attr-name\">data-height</span><span class=\"token attr-value\"><span class=\"token punctuation\">=</span><span class=\"token punctuation\">\"</span>icon-massive<span class=\"token punctuation\">\"</span></span>\n                <span class=\"token attr-name\">style</span><span class=\"token attr-value\"><span class=\"token punctuation\">=</span><span class=\"token punctuation\">\"</span>background: hsl(var(--palettes-affirmative-background-normal));<span class=\"token punctuation\">\"</span></span>\n            <span class=\"token punctuation\">/></span></span>\n\n            <span class=\"token tag\"><span class=\"token tag\"><span class=\"token punctuation\">&lt;</span>div</span>\n                <span class=\"token attr-name\">data-height</span><span class=\"token attr-value\"><span class=\"token punctuation\">=</span><span class=\"token punctuation\">\"</span>icon-massive<span class=\"token punctuation\">\"</span></span>\n                <span class=\"token attr-name\">style</span><span class=\"token attr-value\"><span class=\"token punctuation\">=</span><span class=\"token punctuation\">\"</span>background: hsl(var(--palettes-affirmative-background-bold));<span class=\"token punctuation\">\"</span></span>\n            <span class=\"token punctuation\">/></span></span>\n\n            <span class=\"token tag\"><span class=\"token tag\"><span class=\"token punctuation\">&lt;</span>div</span>\n                <span class=\"token attr-name\">data-height</span><span class=\"token attr-value\"><span class=\"token punctuation\">=</span><span class=\"token punctuation\">\"</span>icon-massive<span class=\"token punctuation\">\"</span></span>\n                <span class=\"token attr-name\">style</span><span class=\"token attr-value\"><span class=\"token punctuation\">=</span><span class=\"token punctuation\">\"</span>background: hsl(var(--palettes-affirmative-background-bolder));<span class=\"token punctuation\">\"</span></span>\n            <span class=\"token punctuation\">/></span></span>\n\n            <span class=\"token tag\"><span class=\"token tag\"><span class=\"token punctuation\">&lt;</span>div</span>\n                <span class=\"token attr-name\">data-height</span><span class=\"token attr-value\"><span class=\"token punctuation\">=</span><span class=\"token punctuation\">\"</span>icon-massive<span class=\"token punctuation\">\"</span></span>\n                <span class=\"token attr-name\">style</span><span class=\"token attr-value\"><span class=\"token punctuation\">=</span><span class=\"token punctuation\">\"</span>background: hsl(var(--palettes-affirmative-background-boldest));<span class=\"token punctuation\">\"</span></span>\n            <span class=\"token punctuation\">/></span></span>\n        <span class=\"token tag\"><span class=\"token tag\"><span class=\"token punctuation\">&lt;/</span>Stack.Container</span><span class=\"token punctuation\">></span></span>\n    <span class=\"token tag\"><span class=\"token tag\"><span class=\"token punctuation\">&lt;/</span>div</span><span class=\"token punctuation\">></span></span>\n\n    <span class=\"token tag\"><span class=\"token tag\"><span class=\"token punctuation\">&lt;</span>div</span><span class=\"token punctuation\">></span></span>\n        <span class=\"token tag\"><span class=\"token tag\"><span class=\"token punctuation\">&lt;</span>Text</span> <span class=\"token attr-name\">is</span><span class=\"token attr-value\"><span class=\"token punctuation\">=</span><span class=\"token punctuation\">\"</span>strong<span class=\"token punctuation\">\"</span></span><span class=\"token punctuation\">></span></span>INFORMATIVE<span class=\"token tag\"><span class=\"token tag\"><span class=\"token punctuation\">&lt;/</span>Text</span><span class=\"token punctuation\">></span></span>\n\n        <span class=\"token tag\"><span class=\"token tag\"><span class=\"token punctuation\">&lt;</span>Stack.Container</span>\n            <span class=\"token attr-name\">orientation</span><span class=\"token attr-value\"><span class=\"token punctuation\">=</span><span class=\"token punctuation\">\"</span>horizontal<span class=\"token punctuation\">\"</span></span>\n            <span class=\"token attr-name\">alignment_x</span><span class=\"token attr-value\"><span class=\"token punctuation\">=</span><span class=\"token punctuation\">\"</span>stretch<span class=\"token punctuation\">\"</span></span>\n        <span class=\"token punctuation\">></span></span>\n            <span class=\"token tag\"><span class=\"token tag\"><span class=\"token punctuation\">&lt;</span>div</span>\n                <span class=\"token attr-name\">data-height</span><span class=\"token attr-value\"><span class=\"token punctuation\">=</span><span class=\"token punctuation\">\"</span>icon-massive<span class=\"token punctuation\">\"</span></span>\n                <span class=\"token attr-name\">style</span><span class=\"token attr-value\"><span class=\"token punctuation\">=</span><span class=\"token punctuation\">\"</span>background: hsl(var(--palettes-informative-background-lightest));<span class=\"token punctuation\">\"</span></span>\n            <span class=\"token punctuation\">/></span></span>\n\n            <span class=\"token tag\"><span class=\"token tag\"><span class=\"token punctuation\">&lt;</span>div</span>\n                <span class=\"token attr-name\">data-height</span><span class=\"token attr-value\"><span class=\"token punctuation\">=</span><span class=\"token punctuation\">\"</span>icon-massive<span class=\"token punctuation\">\"</span></span>\n                <span class=\"token attr-name\">style</span><span class=\"token attr-value\"><span class=\"token punctuation\">=</span><span class=\"token punctuation\">\"</span>background: hsl(var(--palettes-informative-background-lighter));<span class=\"token punctuation\">\"</span></span>\n            <span class=\"token punctuation\">/></span></span>\n\n            <span class=\"token tag\"><span class=\"token tag\"><span class=\"token punctuation\">&lt;</span>div</span>\n                <span class=\"token attr-name\">data-height</span><span class=\"token attr-value\"><span class=\"token punctuation\">=</span><span class=\"token punctuation\">\"</span>icon-massive<span class=\"token punctuation\">\"</span></span>\n                <span class=\"token attr-name\">style</span><span class=\"token attr-value\"><span class=\"token punctuation\">=</span><span class=\"token punctuation\">\"</span>background: hsl(var(--palettes-informative-background-light));<span class=\"token punctuation\">\"</span></span>\n            <span class=\"token punctuation\">/></span></span>\n\n            <span class=\"token tag\"><span class=\"token tag\"><span class=\"token punctuation\">&lt;</span>div</span>\n                <span class=\"token attr-name\">data-height</span><span class=\"token attr-value\"><span class=\"token punctuation\">=</span><span class=\"token punctuation\">\"</span>icon-massive<span class=\"token punctuation\">\"</span></span>\n                <span class=\"token attr-name\">style</span><span class=\"token attr-value\"><span class=\"token punctuation\">=</span><span class=\"token punctuation\">\"</span>background: hsl(var(--palettes-informative-background-normal));<span class=\"token punctuation\">\"</span></span>\n            <span class=\"token punctuation\">/></span></span>\n\n            <span class=\"token tag\"><span class=\"token tag\"><span class=\"token punctuation\">&lt;</span>div</span>\n                <span class=\"token attr-name\">data-height</span><span class=\"token attr-value\"><span class=\"token punctuation\">=</span><span class=\"token punctuation\">\"</span>icon-massive<span class=\"token punctuation\">\"</span></span>\n                <span class=\"token attr-name\">style</span><span class=\"token attr-value\"><span class=\"token punctuation\">=</span><span class=\"token punctuation\">\"</span>background: hsl(var(--palettes-informative-background-bold));<span class=\"token punctuation\">\"</span></span>\n            <span class=\"token punctuation\">/></span></span>\n\n            <span class=\"token tag\"><span class=\"token tag\"><span class=\"token punctuation\">&lt;</span>div</span>\n                <span class=\"token attr-name\">data-height</span><span class=\"token attr-value\"><span class=\"token punctuation\">=</span><span class=\"token punctuation\">\"</span>icon-massive<span class=\"token punctuation\">\"</span></span>\n                <span class=\"token attr-name\">style</span><span class=\"token attr-value\"><span class=\"token punctuation\">=</span><span class=\"token punctuation\">\"</span>background: hsl(var(--palettes-informative-background-bolder));<span class=\"token punctuation\">\"</span></span>\n            <span class=\"token punctuation\">/></span></span>\n\n            <span class=\"token tag\"><span class=\"token tag\"><span class=\"token punctuation\">&lt;</span>div</span>\n                <span class=\"token attr-name\">data-height</span><span class=\"token attr-value\"><span class=\"token punctuation\">=</span><span class=\"token punctuation\">\"</span>icon-massive<span class=\"token punctuation\">\"</span></span>\n                <span class=\"token attr-name\">style</span><span class=\"token attr-value\"><span class=\"token punctuation\">=</span><span class=\"token punctuation\">\"</span>background: hsl(var(--palettes-informative-background-boldest));<span class=\"token punctuation\">\"</span></span>\n            <span class=\"token punctuation\">/></span></span>\n        <span class=\"token tag\"><span class=\"token tag\"><span class=\"token punctuation\">&lt;/</span>Stack.Container</span><span class=\"token punctuation\">></span></span>\n    <span class=\"token tag\"><span class=\"token tag\"><span class=\"token punctuation\">&lt;/</span>div</span><span class=\"token punctuation\">></span></span>\n\n    <span class=\"token tag\"><span class=\"token tag\"><span class=\"token punctuation\">&lt;</span>div</span><span class=\"token punctuation\">></span></span>\n        <span class=\"token tag\"><span class=\"token tag\"><span class=\"token punctuation\">&lt;</span>Text</span> <span class=\"token attr-name\">is</span><span class=\"token attr-value\"><span class=\"token punctuation\">=</span><span class=\"token punctuation\">\"</span>strong<span class=\"token punctuation\">\"</span></span><span class=\"token punctuation\">></span></span>NEGATIVE<span class=\"token tag\"><span class=\"token tag\"><span class=\"token punctuation\">&lt;/</span>Text</span><span class=\"token punctuation\">></span></span>\n\n        <span class=\"token tag\"><span class=\"token tag\"><span class=\"token punctuation\">&lt;</span>Stack.Container</span>\n            <span class=\"token attr-name\">orientation</span><span class=\"token attr-value\"><span class=\"token punctuation\">=</span><span class=\"token punctuation\">\"</span>horizontal<span class=\"token punctuation\">\"</span></span>\n            <span class=\"token attr-name\">alignment_x</span><span class=\"token attr-value\"><span class=\"token punctuation\">=</span><span class=\"token punctuation\">\"</span>stretch<span class=\"token punctuation\">\"</span></span>\n        <span class=\"token punctuation\">></span></span>\n            <span class=\"token tag\"><span class=\"token tag\"><span class=\"token punctuation\">&lt;</span>div</span>\n                <span class=\"token attr-name\">data-height</span><span class=\"token attr-value\"><span class=\"token punctuation\">=</span><span class=\"token punctuation\">\"</span>icon-massive<span class=\"token punctuation\">\"</span></span>\n                <span class=\"token attr-name\">style</span><span class=\"token attr-value\"><span class=\"token punctuation\">=</span><span class=\"token punctuation\">\"</span>background: hsl(var(--palettes-negative-background-lightest));<span class=\"token punctuation\">\"</span></span>\n            <span class=\"token punctuation\">/></span></span>\n\n            <span class=\"token tag\"><span class=\"token tag\"><span class=\"token punctuation\">&lt;</span>div</span>\n                <span class=\"token attr-name\">data-height</span><span class=\"token attr-value\"><span class=\"token punctuation\">=</span><span class=\"token punctuation\">\"</span>icon-massive<span class=\"token punctuation\">\"</span></span>\n                <span class=\"token attr-name\">style</span><span class=\"token attr-value\"><span class=\"token punctuation\">=</span><span class=\"token punctuation\">\"</span>background: hsl(var(--palettes-negative-background-lighter));<span class=\"token punctuation\">\"</span></span>\n            <span class=\"token punctuation\">/></span></span>\n\n            <span class=\"token tag\"><span class=\"token tag\"><span class=\"token punctuation\">&lt;</span>div</span>\n                <span class=\"token attr-name\">data-height</span><span class=\"token attr-value\"><span class=\"token punctuation\">=</span><span class=\"token punctuation\">\"</span>icon-massive<span class=\"token punctuation\">\"</span></span>\n                <span class=\"token attr-name\">style</span><span class=\"token attr-value\"><span class=\"token punctuation\">=</span><span class=\"token punctuation\">\"</span>background: hsl(var(--palettes-negative-background-light));<span class=\"token punctuation\">\"</span></span>\n            <span class=\"token punctuation\">/></span></span>\n\n            <span class=\"token tag\"><span class=\"token tag\"><span class=\"token punctuation\">&lt;</span>div</span>\n                <span class=\"token attr-name\">data-height</span><span class=\"token attr-value\"><span class=\"token punctuation\">=</span><span class=\"token punctuation\">\"</span>icon-massive<span class=\"token punctuation\">\"</span></span>\n                <span class=\"token attr-name\">style</span><span class=\"token attr-value\"><span class=\"token punctuation\">=</span><span class=\"token punctuation\">\"</span>background: hsl(var(--palettes-negative-background-normal));<span class=\"token punctuation\">\"</span></span>\n            <span class=\"token punctuation\">/></span></span>\n\n            <span class=\"token tag\"><span class=\"token tag\"><span class=\"token punctuation\">&lt;</span>div</span>\n                <span class=\"token attr-name\">data-height</span><span class=\"token attr-value\"><span class=\"token punctuation\">=</span><span class=\"token punctuation\">\"</span>icon-massive<span class=\"token punctuation\">\"</span></span>\n                <span class=\"token attr-name\">style</span><span class=\"token attr-value\"><span class=\"token punctuation\">=</span><span class=\"token punctuation\">\"</span>background: hsl(var(--palettes-negative-background-bold));<span class=\"token punctuation\">\"</span></span>\n            <span class=\"token punctuation\">/></span></span>\n\n            <span class=\"token tag\"><span class=\"token tag\"><span class=\"token punctuation\">&lt;</span>div</span>\n                <span class=\"token attr-name\">data-height</span><span class=\"token attr-value\"><span class=\"token punctuation\">=</span><span class=\"token punctuation\">\"</span>icon-massive<span class=\"token punctuation\">\"</span></span>\n                <span class=\"token attr-name\">style</span><span class=\"token attr-value\"><span class=\"token punctuation\">=</span><span class=\"token punctuation\">\"</span>background: hsl(var(--palettes-negative-background-bolder));<span class=\"token punctuation\">\"</span></span>\n            <span class=\"token punctuation\">/></span></span>\n\n            <span class=\"token tag\"><span class=\"token tag\"><span class=\"token punctuation\">&lt;</span>div</span>\n                <span class=\"token attr-name\">data-height</span><span class=\"token attr-value\"><span class=\"token punctuation\">=</span><span class=\"token punctuation\">\"</span>icon-massive<span class=\"token punctuation\">\"</span></span>\n                <span class=\"token attr-name\">style</span><span class=\"token attr-value\"><span class=\"token punctuation\">=</span><span class=\"token punctuation\">\"</span>background: hsl(var(--palettes-negative-background-boldest));<span class=\"token punctuation\">\"</span></span>\n            <span class=\"token punctuation\">/></span></span>\n        <span class=\"token tag\"><span class=\"token tag\"><span class=\"token punctuation\">&lt;/</span>Stack.Container</span><span class=\"token punctuation\">></span></span>\n    <span class=\"token tag\"><span class=\"token tag\"><span class=\"token punctuation\">&lt;/</span>div</span><span class=\"token punctuation\">></span></span>\n<span class=\"token tag\"><span class=\"token tag\"><span class=\"token punctuation\">&lt;/</span>Stack.Container</span><span class=\"token punctuation\">></span></span></code></pre>"}}